himena_image/__init__.py
himena_image/_mgui_widgets.py
himena_image/consts.py
himena_image/ij.py
himena_image/io.py
himena_image/utils.py
himena_image/new/__init__.py
himena_image/processing/__init__.py
himena_image/processing/_hints.py
himena_image/processing/calculate.py
himena_image/processing/exposure.py
himena_image/processing/features.py
himena_image/processing/fft.py
himena_image/processing/filters.py
himena_image/processing/measure.py
himena_image/processing/morphology.py
himena_image/processing/restore.py
himena_image/processing/transform.py
himena_image/widgets/__init__.py
himena_image/widgets/_wrapper.py
himena_image/widgets/viewer.py
himena_image-0.1.2.dist-info/METADATA
himena_image-0.1.2.dist-info/WHEEL
himena_image-0.1.2.dist-info/entry_points.txt
himena_image-0.1.2.dist-info/licenses/LICENSE
himena_image-0.1.2.dist-info/RECORD
