Metadata-Version: 2.4
Name: himena-image
Version: 0.1.2
Summary: Himena plugin for image processing and analysis
Project-URL: Documentation, https://github.com/hanjinliu/himena-image#readme
Project-URL: Issues, https://github.com/hanjinliu/himena-image/issues
Project-URL: Source, https://github.com/hanjinliu/himena-image
Author-email: hanjinliu <liuhanjin.sc@gmail.com>
License: BSD 3-Clause License
License-File: LICENSE
Classifier: Development Status :: 4 - Beta
Classifier: Programming Language :: Python
Classifier: Programming Language :: Python :: 3.10
Classifier: Programming Language :: Python :: 3.11
Classifier: Programming Language :: Python :: 3.12
Classifier: Programming Language :: Python :: 3.13
Classifier: Programming Language :: Python :: 3.14
Classifier: Programming Language :: Python :: Implementation :: CPython
Classifier: Programming Language :: Python :: Implementation :: PyPy
Requires-Python: >=3.10
Requires-Dist: himena>=0.0.13
Requires-Dist: impy-array>=2.5.0
Requires-Dist: ndv
Requires-Dist: roifile>=2024.5.24
Provides-Extra: all
Requires-Dist: mrcfile; extra == 'all'
Requires-Dist: nd2; extra == 'all'
Requires-Dist: tifffile; extra == 'all'
Provides-Extra: testing
Requires-Dist: click!=8.3.0; extra == 'testing'
Requires-Dist: himena[testing]; extra == 'testing'
Requires-Dist: pyqt6; extra == 'testing'
Requires-Dist: pytest; extra == 'testing'
Requires-Dist: pytest-cov; extra == 'testing'
